<Dependencies>
  <ProductDependencies>
    <Dependency Name="System.CommandLine.Experimental" Version="&gt;0.2.0-alpha.19213.1">
      <Uri>https://github.com/dotnet/command-line-api</Uri>
      <Sha>166610c56ff732093f0145a2911d4f6c40b786da</Sha>
    </Dependency>
    <Dependency Name="Microsoft.Diagnostics.Monitoring" Version="5.0.0-preview.21603.1">
      <Uri>https://github.com/dotnet/diagnostics</Uri>
      <Sha>3f3621829b5ed4dc2e87966b5f0cc61b1adf0632</Sha>
    </Dependency>
    <Dependency Name="Microsoft.Diagnostics.Monitoring.EventPipe" Version="5.0.0-preview.21603.1">
      <Uri>https://github.com/dotnet/diagnostics</Uri>
      <Sha>3f3621829b5ed4dc2e87966b5f0cc61b1adf0632</Sha>
    </Dependency>
    <Dependency Name="Microsoft.Extensions.Configuration.KeyPerFile" Version="6.0.1">
      <Uri>https://github.com/dotnet/aspnetcore</Uri>
      <Sha>717740e203a1cfb544d6e10e2aa4fd5f0a5f328d</Sha>
    </Dependency>
    <Dependency Name="Microsoft.Extensions.Logging.Abstractions" Version="6.0.0">
      <Uri>https://github.com/dotnet/runtime</Uri>
      <Sha>4822e3c3aa77eb82b2fb33c9321f923cf11ddde6</Sha>
    </Dependency>
    <Dependency Name="Microsoft.Extensions.Logging.Console" Version="6.0.0">
      <Uri>https://github.com/dotnet/runtime</Uri>
      <Sha>4822e3c3aa77eb82b2fb33c9321f923cf11ddde6</Sha>
    </Dependency>
    <Dependency Name="System.Text.Json" Version="6.0.0">
      <Uri>https://github.com/dotnet/runtime</Uri>
      <Sha>4822e3c3aa77eb82b2fb33c9321f923cf11ddde6</Sha>
    </Dependency>
  </ProductDependencies>
  <ToolsetDependencies>
    <Dependency Name="Microsoft.AspNetCore.App.Runtime.win-x64" Version="6.0.1">
      <Uri>https://github.com/dotnet/aspnetcore</Uri>
      <Sha>717740e203a1cfb544d6e10e2aa4fd5f0a5f328d</Sha>
    </Dependency>
    <Dependency Name="Microsoft.DotNet.Arcade.Sdk" Version="7.0.0-beta.21576.4">
      <Uri>https://github.com/dotnet/arcade</Uri>
      <Sha>427c05909067bb2e484116ae2239456bb45adb85</Sha>
    </Dependency>
    <Dependency Name="Microsoft.DotNet.XUnitExtensions" Version="7.0.0-beta.21576.4">
      <Uri>https://github.com/dotnet/arcade</Uri>
      <Sha>427c05909067bb2e484116ae2239456bb45adb85</Sha>
    </Dependency>
    <Dependency Name="Microsoft.Extensions.Configuration.Abstractions" Version="6.0.0">
      <Uri>https://github.com/dotnet/runtime</Uri>
      <Sha>4822e3c3aa77eb82b2fb33c9321f923cf11ddde6</Sha>
    </Dependency>
    <Dependency Name="Microsoft.Extensions.Logging.EventSource" Version="6.0.0">
      <Uri>https://github.com/dotnet/runtime</Uri>
      <Sha>4822e3c3aa77eb82b2fb33c9321f923cf11ddde6</Sha>
    </Dependency>
    <Dependency Name="Microsoft.FileFormats" Version="1.0.257901">
      <Uri>https://github.com/dotnet/symstore</Uri>
      <Sha>eee46ffedfafeb63fbf6e608f013fc0ff1fba93a</Sha>
    </Dependency>
    <Dependency Name="Microsoft.NETCore.App.Runtime.win-x64" Version="6.0.1">
      <Uri>https://github.com/dotnet/runtime</Uri>
      <Sha>fd61aefcf12382a9ddd24295f660b95606201d57</Sha>
    </Dependency>
    <Dependency Name="VS.Redist.Common.AspNetCore.SharedFramework.x64.6.0" Version="6.0.1-servicing.21565.21">
      <Uri>https://github.com/dotnet/aspnetcore</Uri>
      <Sha>717740e203a1cfb544d6e10e2aa4fd5f0a5f328d</Sha>
    </Dependency>
    <Dependency Name="VS.Redist.Common.NetCore.SharedFramework.x64.6.0" Version="6.0.1-servicing.21566.4">
      <Uri>https://github.com/dotnet/runtime</Uri>
      <Sha>fd61aefcf12382a9ddd24295f660b95606201d57</Sha>
    </Dependency>
  </ToolsetDependencies>
</Dependencies>
