<Dependencies>
  <ProductDependencies>
    <Dependency Name="System.CommandLine.Experimental" Version="&gt;0.2.0-alpha.19213.1">
      <Uri>https://github.com/dotnet/command-line-api</Uri>
      <Sha>166610c56ff732093f0145a2911d4f6c40b786da</Sha>
    </Dependency>
    <Dependency Name="Microsoft.Diagnostics.Monitoring" Version="5.0.0-preview.21427.1">
      <Uri>https://github.com/dotnet/diagnostics</Uri>
      <Sha>08047f42e4fb17f2f9ddc82fc08148875e78273d</Sha>
    </Dependency>
    <Dependency Name="Microsoft.Diagnostics.Monitoring.EventPipe" Version="5.0.0-preview.21427.1">
      <Uri>https://github.com/dotnet/diagnostics</Uri>
      <Sha>08047f42e4fb17f2f9ddc82fc08148875e78273d</Sha>
    </Dependency>
  </ProductDependencies>
  <ToolsetDependencies>
    <Dependency Name="Microsoft.DotNet.Arcade.Sdk" Version="6.0.0-beta.21430.1">
      <Uri>https://github.com/dotnet/arcade</Uri>
      <Sha>e0260cb677c04cb0244aad7537c33bec4adce422</Sha>
    </Dependency>
    <Dependency Name="Microsoft.DotNet.XUnitExtensions" Version="6.0.0-beta.21430.1">
      <Uri>https://github.com/dotnet/arcade</Uri>
      <Sha>e0260cb677c04cb0244aad7537c33bec4adce422</Sha>
    </Dependency>
    <Dependency Name="Microsoft.FileFormats" Version="1.0.242601">
      <Uri>https://github.com/dotnet/symstore</Uri>
      <Sha>22c8e44f32ddce609895b8993491523fad77279b</Sha>
    </Dependency>
    <Dependency Name="VS.Redist.Common.AspNetCore.SharedFramework.x64.6.0" Version="6.0.0-rc.2.21430.41">
      <Uri>https://github.com/dotnet/aspnetcore</Uri>
      <Sha>1fafcfae1bd23cb3dec36099a1e6e0a53e55b83f</Sha>
    </Dependency>
    <Dependency Name="VS.Redist.Common.NetCore.SharedFramework.x64.6.0" Version="6.0.0-rc.2.21430.24">
      <Uri>https://github.com/dotnet/runtime</Uri>
      <Sha>cf20e76971b22a918de02999fec8fdacfaa4c237</Sha>
    </Dependency>
  </ToolsetDependencies>
</Dependencies>
