<Dependencies>
  <ProductDependencies>
    <Dependency Name="System.CommandLine.Experimental" Version="&gt;0.2.0-alpha.19213.1">
      <Uri>https://github.com/dotnet/command-line-api</Uri>
      <Sha>166610c56ff732093f0145a2911d4f6c40b786da</Sha>
    </Dependency>
    <Dependency Name="Microsoft.Diagnostics.Monitoring" Version="5.0.0-preview.22273.1">
      <Uri>https://github.com/dotnet/diagnostics</Uri>
      <Sha>e5ba58f4957213ba79aec25a4bb7f8afb18c19a7</Sha>
    </Dependency>
    <Dependency Name="Microsoft.Diagnostics.Monitoring.EventPipe" Version="5.0.0-preview.22273.1">
      <Uri>https://github.com/dotnet/diagnostics</Uri>
      <Sha>e5ba58f4957213ba79aec25a4bb7f8afb18c19a7</Sha>
    </Dependency>
  </ProductDependencies>
  <ToolsetDependencies>
    <Dependency Name="Microsoft.AspNetCore.App.Runtime.win-x64" Version="7.0.0-preview.5.22274.1">
      <Uri>https://github.com/dotnet/aspnetcore</Uri>
      <Sha>5ff6e316a8e34bb06b986ec13ec7aae3f61e886b</Sha>
    </Dependency>
    <Dependency Name="Microsoft.DotNet.Arcade.Sdk" Version="7.0.0-beta.22274.7">
      <Uri>https://github.com/dotnet/arcade</Uri>
      <Sha>007adcd66f519c3c96fa0ecc21ed197a6da9e015</Sha>
    </Dependency>
    <Dependency Name="Microsoft.DotNet.XUnitExtensions" Version="7.0.0-beta.22274.7">
      <Uri>https://github.com/dotnet/arcade</Uri>
      <Sha>007adcd66f519c3c96fa0ecc21ed197a6da9e015</Sha>
    </Dependency>
    <Dependency Name="Microsoft.FileFormats" Version="1.0.327301">
      <Uri>https://github.com/dotnet/symstore</Uri>
      <Sha>adf3d62fe38ae79afe7ac3da7db13ddba601279a</Sha>
    </Dependency>
    <Dependency Name="Microsoft.NETCore.App.Runtime.win-x64" Version="7.0.0-preview.5.22272.3" CoherentParentDependency="Microsoft.AspNetCore.App.Runtime.win-x64">
      <Uri>https://github.com/dotnet/runtime</Uri>
      <Sha>0864cc5539e0ddd109b443b0bee804878cd7ba76</Sha>
    </Dependency>
    <Dependency Name="VS.Redist.Common.AspNetCore.SharedFramework.x64.7.0" Version="7.0.0-preview.5.22274.1">
      <Uri>https://github.com/dotnet/aspnetcore</Uri>
      <Sha>5ff6e316a8e34bb06b986ec13ec7aae3f61e886b</Sha>
    </Dependency>
    <Dependency Name="VS.Redist.Common.NetCore.SharedFramework.x64.7.0" Version="7.0.0-preview.5.22272.3" CoherentParentDependency="VS.Redist.Common.AspNetCore.SharedFramework.x64.7.0">
      <Uri>https://github.com/dotnet/runtime</Uri>
      <Sha>0864cc5539e0ddd109b443b0bee804878cd7ba76</Sha>
    </Dependency>
  </ToolsetDependencies>
</Dependencies>
