<Dependencies>
  <ProductDependencies>
    <Dependency Name="System.CommandLine.Experimental" Version="&gt;0.2.0-alpha.19213.1">
      <Uri>https://github.com/dotnet/command-line-api</Uri>
      <Sha>166610c56ff732093f0145a2911d4f6c40b786da</Sha>
    </Dependency>
    <Dependency Name="Microsoft.Diagnostics.Monitoring" Version="5.0.0-preview.21212.1">
      <Uri>https://github.com/dotnet/diagnostics</Uri>
      <Sha>43bee2e202124231968f1f710b07a30ba4348a22</Sha>
    </Dependency>
    <Dependency Name="Microsoft.Diagnostics.Monitoring.EventPipe" Version="5.0.0-preview.21212.1">
      <Uri>https://github.com/dotnet/diagnostics</Uri>
      <Sha>43bee2e202124231968f1f710b07a30ba4348a22</Sha>
    </Dependency>
    <Dependency Name="Microsoft.DotNet.XUnitExtensions" Version="6.0.0-beta.21209.17">
      <Uri>https://github.com/dotnet/arcade</Uri>
      <Sha>28d9452d7e2ae4e98a1df735b90b03d3cac1f4e7</Sha>
    </Dependency>
  </ProductDependencies>
  <ToolsetDependencies>
    <Dependency Name="Microsoft.DotNet.Arcade.Sdk" Version="6.0.0-beta.21209.17">
      <Uri>https://github.com/dotnet/arcade</Uri>
      <Sha>28d9452d7e2ae4e98a1df735b90b03d3cac1f4e7</Sha>
    </Dependency>
  </ToolsetDependencies>
</Dependencies>
