<Dependencies>
  <ProductDependencies>
    <Dependency Name="System.CommandLine.Experimental" Version="&gt;0.2.0-alpha.19213.1">
      <Uri>https://github.com/dotnet/command-line-api</Uri>
      <Sha>166610c56ff732093f0145a2911d4f6c40b786da</Sha>
    </Dependency>
    <Dependency Name="Microsoft.Diagnostics.Monitoring" Version="5.0.0-preview.21451.1">
      <Uri>https://github.com/dotnet/diagnostics</Uri>
      <Sha>1c29ec3572602a430aaee61b441e63ba7ed6a5f9</Sha>
    </Dependency>
    <Dependency Name="Microsoft.Diagnostics.Monitoring.EventPipe" Version="5.0.0-preview.21451.1">
      <Uri>https://github.com/dotnet/diagnostics</Uri>
      <Sha>1c29ec3572602a430aaee61b441e63ba7ed6a5f9</Sha>
    </Dependency>
  </ProductDependencies>
  <ToolsetDependencies>
    <Dependency Name="Microsoft.DotNet.Arcade.Sdk" Version="6.0.0-beta.21451.3">
      <Uri>https://github.com/dotnet/arcade</Uri>
      <Sha>923c95ec2e9512285f801c84145a8af3728b1e3b</Sha>
    </Dependency>
    <Dependency Name="Microsoft.DotNet.XUnitExtensions" Version="6.0.0-beta.21451.3">
      <Uri>https://github.com/dotnet/arcade</Uri>
      <Sha>923c95ec2e9512285f801c84145a8af3728b1e3b</Sha>
    </Dependency>
    <Dependency Name="Microsoft.FileFormats" Version="1.0.243001">
      <Uri>https://github.com/dotnet/symstore</Uri>
      <Sha>51ad9dcdfc2e324894ad2ca9e57a582550f72958</Sha>
    </Dependency>
    <Dependency Name="VS.Redist.Common.AspNetCore.SharedFramework.x64.6.0" Version="6.0.0-rc.2.21451.2">
      <Uri>https://github.com/dotnet/aspnetcore</Uri>
      <Sha>9412accc97c36a390208ef2c20197a6d7effa62c</Sha>
    </Dependency>
    <Dependency Name="VS.Redist.Common.NetCore.SharedFramework.x64.6.0" Version="6.0.0-rc.2.21431.13">
      <Uri>https://github.com/dotnet/runtime</Uri>
      <Sha>1e96637ca9bdfcf24e049499123e503eb8049cd0</Sha>
    </Dependency>
  </ToolsetDependencies>
</Dependencies>
