<Dependencies>
  <ProductDependencies>
    <Dependency Name="Microsoft.AspNetCore.App.Runtime.win-x64" Version="9.0.0-preview.4.24173.3" CoherentParentDependency="Microsoft.Dotnet.Sdk.Internal">
      <Uri>https://github.com/dotnet/aspnetcore</Uri>
      <Sha>3f99d45b0b7d8f0427a3d98acc63098694613362</Sha>
    </Dependency>
    <Dependency Name="Microsoft.Diagnostics.Monitoring" Version="8.0.0-preview.24176.3">
      <Uri>https://github.com/dotnet/diagnostics</Uri>
      <Sha>045a07e97ac08d34d769db53c1b28266159bcea2</Sha>
    </Dependency>
    <Dependency Name="Microsoft.Diagnostics.Monitoring.EventPipe" Version="8.0.0-preview.24176.3">
      <Uri>https://github.com/dotnet/diagnostics</Uri>
      <Sha>045a07e97ac08d34d769db53c1b28266159bcea2</Sha>
    </Dependency>
    <Dependency Name="System.CommandLine" Version="2.0.0-beta4.24126.1">
      <Uri>https://github.com/dotnet/command-line-api</Uri>
      <Sha>5ea97af07263ea3ef68a18557c8aa3f7e3200bda</Sha>
    </Dependency>
  </ProductDependencies>
  <ToolsetDependencies>
    <Dependency Name="Microsoft.CodeAnalysis.NetAnalyzers" Version="9.0.0-preview.24170.2">
      <Uri>https://github.com/dotnet/roslyn-analyzers</Uri>
      <Sha>29bdbf5df540dc13d4fe440a1ca7076c6ed65864</Sha>
    </Dependency>
    <Dependency Name="Microsoft.DotNet.Arcade.Sdk" Version="9.0.0-beta.24176.6">
      <Uri>https://github.com/dotnet/arcade</Uri>
      <Sha>b6fada3ec4fa37e08dcbafaa6ddf59213f3f8687</Sha>
    </Dependency>
    <Dependency Name="Microsoft.DotNet.Build.Tasks.Archives" Version="9.0.0-beta.24176.6">
      <Uri>https://github.com/dotnet/arcade</Uri>
      <Sha>b6fada3ec4fa37e08dcbafaa6ddf59213f3f8687</Sha>
    </Dependency>
    <Dependency Name="Microsoft.DotNet.CodeAnalysis" Version="9.0.0-beta.24176.6">
      <Uri>https://github.com/dotnet/arcade</Uri>
      <Sha>b6fada3ec4fa37e08dcbafaa6ddf59213f3f8687</Sha>
    </Dependency>
    <Dependency Name="Microsoft.DotNet.Helix.Sdk" Version="9.0.0-beta.24176.6">
      <Uri>https://github.com/dotnet/arcade</Uri>
      <Sha>b6fada3ec4fa37e08dcbafaa6ddf59213f3f8687</Sha>
    </Dependency>
    <Dependency Name="Microsoft.Dotnet.Sdk.Internal" Version="9.0.100-preview.4.24177.2">
      <Uri>https://github.com/dotnet/installer</Uri>
      <Sha>5b126d785162534f50d7fbb1ada827060d38c6d8</Sha>
    </Dependency>
    <Dependency Name="Microsoft.DotNet.XUnitExtensions" Version="9.0.0-beta.24176.6">
      <Uri>https://github.com/dotnet/arcade</Uri>
      <Sha>b6fada3ec4fa37e08dcbafaa6ddf59213f3f8687</Sha>
    </Dependency>
    <Dependency Name="Microsoft.FileFormats" Version="1.0.517501">
      <Uri>https://github.com/dotnet/symstore</Uri>
      <Sha>550601c12a227c87ded32316345934101a8a2422</Sha>
    </Dependency>
    <Dependency Name="Microsoft.NETCore.App.Runtime.win-x64" Version="9.0.0-preview.4.24176.9" CoherentParentDependency="Microsoft.Dotnet.Sdk.Internal">
      <Uri>https://github.com/dotnet/runtime</Uri>
      <Sha>e04d9aa773e18b4946e0dce27a8877828c73d226</Sha>
    </Dependency>
    <Dependency Name="VS.Redist.Common.AspNetCore.SharedFramework.x64.9.0" Version="9.0.0-preview.4.24173.3" CoherentParentDependency="Microsoft.Dotnet.Sdk.Internal">
      <Uri>https://github.com/dotnet/aspnetcore</Uri>
      <Sha>3f99d45b0b7d8f0427a3d98acc63098694613362</Sha>
    </Dependency>
    <Dependency Name="VS.Redist.Common.NetCore.SharedFramework.x64.9.0" Version="9.0.0-preview.4.24176.9" CoherentParentDependency="Microsoft.Dotnet.Sdk.Internal">
      <Uri>https://github.com/dotnet/runtime</Uri>
      <Sha>e04d9aa773e18b4946e0dce27a8877828c73d226</Sha>
    </Dependency>
  </ToolsetDependencies>
</Dependencies>
